{
	"name": "relationship-cjfyahobpv",
	"properties": {
		"Name": "relationship-cjfyahobpv",
		"EntityType": "RELATIONSHIP",
		"Namespace": {
			"DatabaseName": "RetailTemplateDB"
		},
		"Origin": {
			"Type": "SPARK"
		},
		"FromTableName": "TransactionLineItem",
		"ToTableName": "TransactionLineItem",
		"ColumnRelationshipInformations": [
			{
				"FromColumnName": "TransactionId",
				"ToColumnName": "ReturnOfTransactionId"
			},
			{
				"FromColumnName": "TransactionLineItemId",
				"ToColumnName": "ReturnOfTransactionLineItemId"
			}
		],
		"RelationshipType": 0,
		"Properties": {
			"DerivedModelRelationshipInfo": "{\"baseRelationship\":{\"fromEntity\":\"TransactionLineItem.cdm.json/TransactionLineItem\",\"toEntity\":\"TransactionLineItem.cdm.json/TransactionLineItem\",\"joinPairs\":[{\"fromAttribute\":\"TransactionId\",\"toAttribute\":\"ReturnOfTransactionId\"},{\"fromAttribute\":\"TransactionLineItemId\",\"toAttribute\":\"ReturnOfTransactionLineItemId\"}]}}"
		},
		"PublishStatus": "PUBLISHED",
		"ObjectVersion": 3,
		"ObjectId": "732c3542-06bc-4c52-8118-1af9fbdbfce1"
	},
	"type": "RELATIONSHIP"
}